osmsc/__init__.py
osmsc/__version__.py
osmsc/cityjson.py
osmsc/cityobject.py
osmsc/feature.py
osmsc/fusion.py
osmsc/geogroup.py
osmsc/grid.py
osmsc/plot.py
osmsc/utils.py
osmsc-0.1.20.dist-info/METADATA
osmsc-0.1.20.dist-info/WHEEL
osmsc-0.1.20.dist-info/top_level.txt
osmsc-0.1.20.dist-info/RECORD
